regression/VERSION
regression/__init__.py
regression/config.yml
regression/pipeline.py
regression/predict.py
regression/train_pipeline.py
regression/config/__init__.py
regression/config/core.py
regression/datasets/__init__.py
regression/datasets/test.csv
regression/datasets/train.csv
regression/processing/__init__.py
regression/processing/data_manager.py
regression/processing/validation.py
regression/trained_models/__init__.py
regression/trained_models/loan_pred_regression_model_output_v0.0.1.pkl
loan_amount_regression_model-0.0.2.dist-info/METADATA
loan_amount_regression_model-0.0.2.dist-info/WHEEL
loan_amount_regression_model-0.0.2.dist-info/top_level.txt
loan_amount_regression_model-0.0.2.dist-info/RECORD
